.gitignore
AUTHORS.rst
ChangeLog.rst
MANIFEST.in
README.rst
run-tests.sh
setup.py
interception/__init__.py
interception/interception.py
py_interception.egg-info/PKG-INFO
py_interception.egg-info/SOURCES.txt
py_interception.egg-info/dependency_links.txt
py_interception.egg-info/not-zip-safe
py_interception.egg-info/requires.txt
py_interception.egg-info/top_level.txt
tests/__init__.py
tests/p/__init__.py
tests/p/test_all.py
tests/p3/__init__.py
tests/p3/test_all.py