Metadata-Version: 1.1
Name: py-interception
Version: 1.0
Summary: Method Interception with Dependency Injection implementation.
Home-page: https://github.com/moisespsena/py_interception
Author: Moises P. Sena
Author-email: moisespsena@gmail.com
License: BSD
Keywords: utils utilities di dependecy injection intercept interception
Platform: UNKNOWN
Classifier: Development Status :: 5 - Production/Stable
Classifier: Topic :: Utilities
Classifier: Intended Audience :: Developers
Classifier: License :: OSI Approved :: BSD License
Classifier: Operating System :: OS Independent
Classifier: Programming Language :: Python
Classifier: Programming Language :: Python :: 2
Classifier: Programming Language :: Python :: 3
